preprodata/__init__.py
preprodata/clean.py
preprodata/preprocess.py
PreProData-0.3.dist-info/METADATA
PreProData-0.3.dist-info/WHEEL
PreProData-0.3.dist-info/top_level.txt
PreProData-0.3.dist-info/RECORD
