Metadata-Version: 2.1
Name: PreProData
Version: 0.3
Requires-Dist: scikit-learn
